{"key":"Classifying of images","elapsedTime":196776699,"timeFormat":"microseconds","metadata":{"threadCount":4,"tagged count":365},"childs":[{"key":"Classifier","elapsedTime":196744238,"timeFormat":"microseconds","metadata":{},"childs":[{"key":"Setup of classifier","elapsedTime":71690,"timeFormat":"microseconds","metadata":{},"childs":[]},{"key":"Loading of images","elapsedTime":255,"timeFormat":"microseconds","metadata":{},"childs":[]},{"key":"Classify Image","elapsedTime":1867193,"timeFormat":"microseconds","metadata":{},"childs":[]},{"key":"Update Repo","elapsedTime":2543,"timeFormat":"microseconds","metadata":{},"childs":[]},{"key":"Loading of images","elapsedTime":126,"timeFormat":"microseconds","metadata":{},"childs":[]},{"key":"Classify Image","elapsedTime":1837188,"timeFormat":"microseconds","metadata":{},"childs":[]},{"key":"Update Repo","elapsedTime":1950,"timeFormat":"microseconds","metadata":{},"childs":[]},{"key":"Loading of images","elapsedTime":91,"timeFormat":"microseconds","metadata":{},"childs":[]},{"key":"Classify Image","elapsedTime":1857353,"timeFormat":"microseconds","metadata":{},"childs":[]},{"key":"Update Repo","elapsedTime":5084,"timeFormat":"microseconds","metadata":{},"childs":[]},{"key":"Loading of images","elapsedTime":104,"timeFormat":"microseconds","metadata":{},"childs":[]},{"key":"Classify Image","elapsedTime":1822924,"timeFormat":"microseconds","metadata":{},"childs":[]},{"key":"Update Repo","elapsedTime":1871,"timeFormat":"microseconds","metadata":{},"childs":[]},{"key":"Loading of images","elapsedTime":117,"timeFormat":"microseconds","metadata":{},"childs":[]},{"key":"Classify Image","elapsedTime":2120565,"timeFormat":"microseconds","metadata":{},"childs":[]},{"key":"Update Repo","elapsedTime":2463,"timeFormat":"microseconds","metadata":{},"childs":[]},{"key":"Loading of images","elapsedTime":195,"timeFormat":"microseconds","metadata":{},"childs":[]},{"key":"Classify Image","elapsedTime":2202021,"timeFormat":"microseconds","metadata":{},"childs":[]},{"key":"Update Repo","elapsedTime":1981,"timeFormat":"microseconds","metadata":{},"childs":[]},{"key":"Loading of images","elapsedTime":103,"timeFormat":"microseconds","metadata":{},"childs":[]},{"key":"Classify Image","elapsedTime":2063283,"timeFormat":"microseconds","metadata":{},"childs":[]},{"key":"Update Repo","elapsedTime":1710,"timeFormat":"microseconds","metadata":{},"childs":[]},{"key":"Loading of images","elapsedTime":101,"timeFormat":"microseconds","metadata":{},"childs":[]},{"key":"Classify Image","elapsedTime":2047948,"timeFormat":"microseconds","metadata":{},"childs":[]},{"key":"Update Repo","elapsedTime":2475,"timeFormat":"microseconds","metadata":{},"childs":[]},{"key":"Loading of images","elapsedTime":196,"timeFormat":"microseconds","metadata":{},"childs":[]},{"key":"Classify Image","elapsedTime":2201083,"timeFormat":"microseconds","metadata":{},"childs":[]},{"key":"Update Repo","elapsedTime":1754,"timeFormat":"microseconds","metadata":{},"childs":[]},{"key":"Loading of images","elapsedTime":105,"timeFormat":"microseconds","metadata":{},"childs":[]},{"key":"Classify Image","elapsedTime":1947267,"timeFormat":"microseconds","metadata":{},"childs":[]},{"key":"Update Repo","elapsedTime":1726,"timeFormat":"microseconds","metadata":{},"childs":[]},{"key":"Loading of images","elapsedTime":112,"timeFormat":"microseconds","metadata":{},"childs":[]},{"key":"Classify Image","elapsedTime":2262773,"timeFormat":"microseconds","metadata":{},"childs":[]},{"key":"Update Repo","elapsedTime":1735,"timeFormat":"microseconds","metadata":{},"childs":[]},{"key":"Loading of images","elapsedTime":92,"timeFormat":"microseconds","metadata":{},"childs":[]},{"key":"Classify Image","elapsedTime":1934183,"timeFormat":"microseconds","metadata":{},"childs":[]},{"key":"Update Repo","elapsedTime":1771,"timeFormat":"microseconds","metadata":{},"childs":[]},{"key":"Loading of images","elapsedTime":96,"timeFormat":"microseconds","metadata":{},"childs":[]},{"key":"Classify Image","elapsedTime":1946774,"timeFormat":"microseconds","metadata":{},"childs":[]},{"key":"Update Repo","elapsedTime":1757,"timeFormat":"microseconds","metadata":{},"childs":[]},{"key":"Loading of images","elapsedTime":226,"timeFormat":"microseconds","metadata":{},"childs":[]},{"key":"Classify Image","elapsedTime":2291014,"timeFormat":"microseconds","metadata":{},"childs":[]},{"key":"Update Repo","elapsedTime":1693,"timeFormat":"microseconds","metadata":{},"childs":[]},{"key":"Loading of images","elapsedTime":99,"timeFormat":"microseconds","metadata":{},"childs":[]},{"key":"Classify Image","elapsedTime":2150103,"timeFormat":"microseconds","metadata":{},"childs":[]},{"key":"Update Repo","elapsedTime":1739,"timeFormat":"microseconds","metadata":{},"childs":[]},{"key":"Loading of images","elapsedTime":87,"timeFormat":"microseconds","metadata":{},"childs":[]},{"key":"Classify Image","elapsedTime":2069027,"timeFormat":"microseconds","metadata":{},"childs":[]},{"key":"Update Repo","elapsedTime":1789,"timeFormat":"microseconds","metadata":{},"childs":[]},{"key":"Loading of images","elapsedTime":96,"timeFormat":"microseconds","metadata":{},"childs":[]},{"key":"Classify Image","elapsedTime":2199010,"timeFormat":"microseconds","metadata":{},"childs":[]},{"key":"Update Repo","elapsedTime":1949,"timeFormat":"microseconds","metadata":{},"childs":[]},{"key":"Loading of images","elapsedTime":153,"timeFormat":"microseconds","metadata":{},"childs":[]},{"key":"Classify Image","elapsedTime":2250628,"timeFormat":"microseconds","metadata":{},"childs":[]},{"key":"Update Repo","elapsedTime":3617,"timeFormat":"microseconds","metadata":{},"childs":[]},{"key":"Loading of images","elapsedTime":92,"timeFormat":"microseconds","metadata":{},"childs":[]},{"key":"Classify Image","elapsedTime":2240799,"timeFormat":"microseconds","metadata":{},"childs":[]},{"key":"Update Repo","elapsedTime":5210,"timeFormat":"microseconds","metadata":{},"childs":[]},{"key":"Loading of images","elapsedTime":239,"timeFormat":"microseconds","metadata":{},"childs":[]},{"key":"Classify Image","elapsedTime":2332870,"timeFormat":"microseconds","metadata":{},"childs":[]},{"key":"Update Repo","elapsedTime":814,"timeFormat":"microseconds","metadata":{},"childs":[]},{"key":"Loading of images","elapsedTime":90,"timeFormat":"microseconds","metadata":{},"childs":[]},{"key":"Classify Image","elapsedTime":2305190,"timeFormat":"microseconds","metadata":{},"childs":[]},{"key":"Update Repo","elapsedTime":3363,"timeFormat":"microseconds","metadata":{},"childs":[]},{"key":"Loading of images","elapsedTime":108,"timeFormat":"microseconds","metadata":{},"childs":[]},{"key":"Classify Image","elapsedTime":2045517,"timeFormat":"microseconds","metadata":{},"childs":[]},{"key":"Update Repo","elapsedTime":3332,"timeFormat":"microseconds","metadata":{},"childs":[]},{"key":"Loading of images","elapsedTime":104,"timeFormat":"microseconds","metadata":{},"childs":[]},{"key":"Classify Image","elapsedTime":1899520,"timeFormat":"microseconds","metadata":{},"childs":[]},{"key":"Update Repo","elapsedTime":3460,"timeFormat":"microseconds","metadata":{},"childs":[]},{"key":"Loading of images","elapsedTime":108,"timeFormat":"microseconds","metadata":{},"childs":[]},{"key":"Classify Image","elapsedTime":2432499,"timeFormat":"microseconds","metadata":{},"childs":[]},{"key":"Update Repo","elapsedTime":3344,"timeFormat":"microseconds","metadata":{},"childs":[]},{"key":"Loading of images","elapsedTime":103,"timeFormat":"microseconds","metadata":{},"childs":[]},{"key":"Classify Image","elapsedTime":2130933,"timeFormat":"microseconds","metadata":{},"childs":[]},{"key":"Update Repo","elapsedTime":3793,"timeFormat":"microseconds","metadata":{},"childs":[]},{"key":"Loading of images","elapsedTime":201,"timeFormat":"microseconds","metadata":{},"childs":[]},{"key":"Classify Image","elapsedTime":2115755,"timeFormat":"microseconds","metadata":{},"childs":[]},{"key":"Update Repo","elapsedTime":3272,"timeFormat":"microseconds","metadata":{},"childs":[]},{"key":"Loading of images","elapsedTime":127,"timeFormat":"microseconds","metadata":{},"childs":[]},{"key":"Classify Image","elapsedTime":2187111,"timeFormat":"microseconds","metadata":{},"childs":[]},{"key":"Update Repo","elapsedTime":1845,"timeFormat":"microseconds","metadata":{},"childs":[]},{"key":"Loading of images","elapsedTime":101,"timeFormat":"microseconds","metadata":{},"childs":[]},{"key":"Classify Image","elapsedTime":2586551,"timeFormat":"microseconds","metadata":{},"childs":[]},{"key":"Update Repo","elapsedTime":2384,"timeFormat":"microseconds","metadata":{},"childs":[]},{"key":"Loading of images","elapsedTime":189,"timeFormat":"microseconds","metadata":{},"childs":[]},{"key":"Classify Image","elapsedTime":2234146,"timeFormat":"microseconds","metadata":{},"childs":[]},{"key":"Update Repo","elapsedTime":1762,"timeFormat":"microseconds","metadata":{},"childs":[]},{"key":"Loading of images","elapsedTime":106,"timeFormat":"microseconds","metadata":{},"childs":[]},{"key":"Classify Image","elapsedTime":1928539,"timeFormat":"microseconds","metadata":{},"childs":[]},{"key":"Update Repo","elapsedTime":952,"timeFormat":"microseconds","metadata":{},"childs":[]},{"key":"Loading of images","elapsedTime":142,"timeFormat":"microseconds","metadata":{},"childs":[]},{"key":"Classify Image","elapsedTime":2251491,"timeFormat":"microseconds","metadata":{},"childs":[]},{"key":"Update Repo","elapsedTime":39001,"timeFormat":"microseconds","metadata":{},"childs":[]},{"key":"Loading of images","elapsedTime":96,"timeFormat":"microseconds","metadata":{},"childs":[]},{"key":"Classify Image","elapsedTime":2266719,"timeFormat":"microseconds","metadata":{},"childs":[]},{"key":"Update Repo","elapsedTime":1765,"timeFormat":"microseconds","metadata":{},"childs":[]},{"key":"Loading of images","elapsedTime":95,"timeFormat":"microseconds","metadata":{},"childs":[]},{"key":"Classify Image","elapsedTime":2319151,"timeFormat":"microseconds","metadata":{},"childs":[]},{"key":"Update Repo","elapsedTime":2363,"timeFormat":"microseconds","metadata":{},"childs":[]},{"key":"Loading of images","elapsedTime":164,"timeFormat":"microseconds","metadata":{},"childs":[]},{"key":"Classify Image","elapsedTime":2231632,"timeFormat":"microseconds","metadata":{},"childs":[]},{"key":"Update Repo","elapsedTime":2049,"timeFormat":"microseconds","metadata":{},"childs":[]},{"key":"Loading of images","elapsedTime":129,"timeFormat":"microseconds","metadata":{},"childs":[]},{"key":"Classify Image","elapsedTime":1993832,"timeFormat":"microseconds","metadata":{},"childs":[]},{"key":"Update Repo","elapsedTime":1871,"timeFormat":"microseconds","metadata":{},"childs":[]},{"key":"Loading of images","elapsedTime":110,"timeFormat":"microseconds","metadata":{},"childs":[]},{"key":"Classify Image","elapsedTime":2325066,"timeFormat":"microseconds","metadata":{},"childs":[]},{"key":"Update Repo","elapsedTime":2018,"timeFormat":"microseconds","metadata":{},"childs":[]},{"key":"Loading of images","elapsedTime":98,"timeFormat":"microseconds","metadata":{},"childs":[]},{"key":"Classify Image","elapsedTime":2438064,"timeFormat":"microseconds","metadata":{},"childs":[]},{"key":"Update Repo","elapsedTime":1717,"timeFormat":"microseconds","metadata":{},"childs":[]},{"key":"Loading of images","elapsedTime":97,"timeFormat":"microseconds","metadata":{},"childs":[]},{"key":"Classify Image","elapsedTime":2369998,"timeFormat":"microseconds","metadata":{},"childs":[]},{"key":"Update Repo","elapsedTime":45860,"timeFormat":"microseconds","metadata":{},"childs":[]},{"key":"Loading of images","elapsedTime":104,"timeFormat":"microseconds","metadata":{},"childs":[]},{"key":"Classify Image","elapsedTime":2319735,"timeFormat":"microseconds","metadata":{},"childs":[]},{"key":"Update Repo","elapsedTime":1035,"timeFormat":"microseconds","metadata":{},"childs":[]},{"key":"Loading of images","elapsedTime":96,"timeFormat":"microseconds","metadata":{},"childs":[]},{"key":"Classify Image","elapsedTime":2295940,"timeFormat":"microseconds","metadata":{},"childs":[]},{"key":"Update Repo","elapsedTime":1748,"timeFormat":"microseconds","metadata":{},"childs":[]},{"key":"Loading of images","elapsedTime":94,"timeFormat":"microseconds","metadata":{},"childs":[]},{"key":"Classify Image","elapsedTime":2315232,"timeFormat":"microseconds","metadata":{},"childs":[]},{"key":"Update Repo","elapsedTime":1697,"timeFormat":"microseconds","metadata":{},"childs":[]},{"key":"Loading of images","elapsedTime":84,"timeFormat":"microseconds","metadata":{},"childs":[]},{"key":"Classify Image","elapsedTime":2064376,"timeFormat":"microseconds","metadata":{},"childs":[]},{"key":"Update Repo","elapsedTime":1747,"timeFormat":"microseconds","metadata":{},"childs":[]},{"key":"Loading of images","elapsedTime":96,"timeFormat":"microseconds","metadata":{},"childs":[]},{"key":"Classify Image","elapsedTime":2159578,"timeFormat":"microseconds","metadata":{},"childs":[]},{"key":"Update Repo","elapsedTime":7226,"timeFormat":"microseconds","metadata":{},"childs":[]},{"key":"Loading of images","elapsedTime":116,"timeFormat":"microseconds","metadata":{},"childs":[]},{"key":"Classify Image","elapsedTime":2154127,"timeFormat":"microseconds","metadata":{},"childs":[]},{"key":"Update Repo","elapsedTime":1733,"timeFormat":"microseconds","metadata":{},"childs":[]},{"key":"Loading of images","elapsedTime":93,"timeFormat":"microseconds","metadata":{},"childs":[]},{"key":"Classify Image","elapsedTime":1954046,"timeFormat":"microseconds","metadata":{},"childs":[]},{"key":"Update Repo","elapsedTime":1780,"timeFormat":"microseconds","metadata":{},"childs":[]},{"key":"Loading of images","elapsedTime":92,"timeFormat":"microseconds","metadata":{},"childs":[]},{"key":"Classify Image","elapsedTime":2237599,"timeFormat":"microseconds","metadata":{},"childs":[]},{"key":"Update Repo","elapsedTime":16680,"timeFormat":"microseconds","metadata":{},"childs":[]},{"key":"Loading of images","elapsedTime":102,"timeFormat":"microseconds","metadata":{},"childs":[]},{"key":"Classify Image","elapsedTime":2300126,"timeFormat":"microseconds","metadata":{},"childs":[]},{"key":"Update Repo","elapsedTime":1753,"timeFormat":"microseconds","metadata":{},"childs":[]},{"key":"Loading of images","elapsedTime":100,"timeFormat":"microseconds","metadata":{},"childs":[]},{"key":"Classify Image","elapsedTime":1973914,"timeFormat":"microseconds","metadata":{},"childs":[]},{"key":"Update Repo","elapsedTime":2348,"timeFormat":"microseconds","metadata":{},"childs":[]},{"key":"Loading of images","elapsedTime":98,"timeFormat":"microseconds","metadata":{},"childs":[]},{"key":"Classify Image","elapsedTime":2367514,"timeFormat":"microseconds","metadata":{},"childs":[]},{"key":"Update Repo","elapsedTime":1979,"timeFormat":"microseconds","metadata":{},"childs":[]},{"key":"Loading of images","elapsedTime":95,"timeFormat":"microseconds","metadata":{},"childs":[]},{"key":"Classify Image","elapsedTime":2043552,"timeFormat":"microseconds","metadata":{},"childs":[]},{"key":"Update Repo","elapsedTime":1764,"timeFormat":"microseconds","metadata":{},"childs":[]},{"key":"Loading of images","elapsedTime":95,"timeFormat":"microseconds","metadata":{},"childs":[]},{"key":"Classify Image","elapsedTime":2191735,"timeFormat":"microseconds","metadata":{},"childs":[]},{"key":"Update Repo","elapsedTime":1775,"timeFormat":"microseconds","metadata":{},"childs":[]},{"key":"Loading of images","elapsedTime":117,"timeFormat":"microseconds","metadata":{},"childs":[]},{"key":"Classify Image","elapsedTime":2340573,"timeFormat":"microseconds","metadata":{},"childs":[]},{"key":"Update Repo","elapsedTime":2512,"timeFormat":"microseconds","metadata":{},"childs":[]},{"key":"Loading of images","elapsedTime":205,"timeFormat":"microseconds","metadata":{},"childs":[]},{"key":"Classify Image","elapsedTime":2188122,"timeFormat":"microseconds","metadata":{},"childs":[]},{"key":"Update Repo","elapsedTime":2081,"timeFormat":"microseconds","metadata":{},"childs":[]},{"key":"Loading of images","elapsedTime":103,"timeFormat":"microseconds","metadata":{},"childs":[]},{"key":"Classify Image","elapsedTime":2166505,"timeFormat":"microseconds","metadata":{},"childs":[]},{"key":"Update Repo","elapsedTime":2585,"timeFormat":"microseconds","metadata":{},"childs":[]},{"key":"Loading of images","elapsedTime":115,"timeFormat":"microseconds","metadata":{},"childs":[]},{"key":"Classify Image","elapsedTime":2122359,"timeFormat":"microseconds","metadata":{},"childs":[]},{"key":"Update Repo","elapsedTime":2199,"timeFormat":"microseconds","metadata":{},"childs":[]},{"key":"Loading of images","elapsedTime":94,"timeFormat":"microseconds","metadata":{},"childs":[]},{"key":"Classify Image","elapsedTime":2067244,"timeFormat":"microseconds","metadata":{},"childs":[]},{"key":"Update Repo","elapsedTime":1743,"timeFormat":"microseconds","metadata":{},"childs":[]},{"key":"Loading of images","elapsedTime":100,"timeFormat":"microseconds","metadata":{},"childs":[]},{"key":"Classify Image","elapsedTime":2065934,"timeFormat":"microseconds","metadata":{},"childs":[]},{"key":"Update Repo","elapsedTime":1778,"timeFormat":"microseconds","metadata":{},"childs":[]},{"key":"Loading of images","elapsedTime":118,"timeFormat":"microseconds","metadata":{},"childs":[]},{"key":"Classify Image","elapsedTime":2328812,"timeFormat":"microseconds","metadata":{},"childs":[]},{"key":"Update Repo","elapsedTime":666,"timeFormat":"microseconds","metadata":{},"childs":[]},{"key":"Loading of images","elapsedTime":93,"timeFormat":"microseconds","metadata":{},"childs":[]},{"key":"Classify Image","elapsedTime":1924304,"timeFormat":"microseconds","metadata":{},"childs":[]},{"key":"Update Repo","elapsedTime":1571,"timeFormat":"microseconds","metadata":{},"childs":[]},{"key":"Loading of images","elapsedTime":189,"timeFormat":"microseconds","metadata":{},"childs":[]},{"key":"Classify Image","elapsedTime":2399610,"timeFormat":"microseconds","metadata":{},"childs":[]},{"key":"Update Repo","elapsedTime":1731,"timeFormat":"microseconds","metadata":{},"childs":[]},{"key":"Loading of images","elapsedTime":99,"timeFormat":"microseconds","metadata":{},"childs":[]},{"key":"Classify Image","elapsedTime":2323962,"timeFormat":"microseconds","metadata":{},"childs":[]},{"key":"Update Repo","elapsedTime":605,"timeFormat":"microseconds","metadata":{},"childs":[]},{"key":"Loading of images","elapsedTime":100,"timeFormat":"microseconds","metadata":{},"childs":[]},{"key":"Classify Image","elapsedTime":2030972,"timeFormat":"microseconds","metadata":{},"childs":[]},{"key":"Update Repo","elapsedTime":1779,"timeFormat":"microseconds","metadata":{},"childs":[]},{"key":"Loading of images","elapsedTime":101,"timeFormat":"microseconds","metadata":{},"childs":[]},{"key":"Classify Image","elapsedTime":2204081,"timeFormat":"microseconds","metadata":{},"childs":[]},{"key":"Update Repo","elapsedTime":1037,"timeFormat":"microseconds","metadata":{},"childs":[]},{"key":"Loading of images","elapsedTime":88,"timeFormat":"microseconds","metadata":{},"childs":[]},{"key":"Classify Image","elapsedTime":2067809,"timeFormat":"microseconds","metadata":{},"childs":[]},{"key":"Update Repo","elapsedTime":8433,"timeFormat":"microseconds","metadata":{},"childs":[]},{"key":"Loading of images","elapsedTime":98,"timeFormat":"microseconds","metadata":{},"childs":[]},{"key":"Classify Image","elapsedTime":2002304,"timeFormat":"microseconds","metadata":{},"childs":[]},{"key":"Update Repo","elapsedTime":1916,"timeFormat":"microseconds","metadata":{},"childs":[]},{"key":"Loading of images","elapsedTime":104,"timeFormat":"microseconds","metadata":{},"childs":[]},{"key":"Classify Image","elapsedTime":2302146,"timeFormat":"microseconds","metadata":{},"childs":[]},{"key":"Update Repo","elapsedTime":1751,"timeFormat":"microseconds","metadata":{},"childs":[]},{"key":"Loading of images","elapsedTime":102,"timeFormat":"microseconds","metadata":{},"childs":[]},{"key":"Classify Image","elapsedTime":2046340,"timeFormat":"microseconds","metadata":{},"childs":[]},{"key":"Update Repo","elapsedTime":5312,"timeFormat":"microseconds","metadata":{},"childs":[]},{"key":"Loading of images","elapsedTime":112,"timeFormat":"microseconds","metadata":{},"childs":[]},{"key":"Classify Image","elapsedTime":2082662,"timeFormat":"microseconds","metadata":{},"childs":[]},{"key":"Update Repo","elapsedTime":1087,"timeFormat":"microseconds","metadata":{},"childs":[]},{"key":"Loading of images","elapsedTime":180,"timeFormat":"microseconds","metadata":{},"childs":[]},{"key":"Classify Image","elapsedTime":2353929,"timeFormat":"microseconds","metadata":{},"childs":[]},{"key":"Update Repo","elapsedTime":1731,"timeFormat":"microseconds","metadata":{},"childs":[]},{"key":"Loading of images","elapsedTime":90,"timeFormat":"microseconds","metadata":{},"childs":[]},{"key":"Classify Image","elapsedTime":2021020,"timeFormat":"microseconds","metadata":{},"childs":[]},{"key":"Update Repo","elapsedTime":740,"timeFormat":"microseconds","metadata":{},"childs":[]},{"key":"Loading of images","elapsedTime":100,"timeFormat":"microseconds","metadata":{},"childs":[]},{"key":"Classify Image","elapsedTime":1848789,"timeFormat":"microseconds","metadata":{},"childs":[]},{"key":"Update Repo","elapsedTime":728,"timeFormat":"microseconds","metadata":{},"childs":[]},{"key":"Loading of images","elapsedTime":109,"timeFormat":"microseconds","metadata":{},"childs":[]},{"key":"Classify Image","elapsedTime":2085597,"timeFormat":"microseconds","metadata":{},"childs":[]},{"key":"Update Repo","elapsedTime":1909,"timeFormat":"microseconds","metadata":{},"childs":[]},{"key":"Loading of images","elapsedTime":91,"timeFormat":"microseconds","metadata":{},"childs":[]},{"key":"Classify Image","elapsedTime":2136613,"timeFormat":"microseconds","metadata":{},"childs":[]},{"key":"Update Repo","elapsedTime":1728,"timeFormat":"microseconds","metadata":{},"childs":[]},{"key":"Loading of images","elapsedTime":103,"timeFormat":"microseconds","metadata":{},"childs":[]},{"key":"Classify Image","elapsedTime":2086175,"timeFormat":"microseconds","metadata":{},"childs":[]},{"key":"Update Repo","elapsedTime":1728,"timeFormat":"microseconds","metadata":{},"childs":[]},{"key":"Loading of images","elapsedTime":104,"timeFormat":"microseconds","metadata":{},"childs":[]},{"key":"Classify Image","elapsedTime":2153769,"timeFormat":"microseconds","metadata":{},"childs":[]},{"key":"Update Repo","elapsedTime":2360,"timeFormat":"microseconds","metadata":{},"childs":[]},{"key":"Loading of images","elapsedTime":109,"timeFormat":"microseconds","metadata":{},"childs":[]},{"key":"Classify Image","elapsedTime":2333692,"timeFormat":"microseconds","metadata":{},"childs":[]},{"key":"Update Repo","elapsedTime":1798,"timeFormat":"microseconds","metadata":{},"childs":[]},{"key":"Loading of images","elapsedTime":103,"timeFormat":"microseconds","metadata":{},"childs":[]},{"key":"Classify Image","elapsedTime":2153106,"timeFormat":"microseconds","metadata":{},"childs":[]},{"key":"Update Repo","elapsedTime":1203,"timeFormat":"microseconds","metadata":{},"childs":[]},{"key":"Loading of images","elapsedTime":314,"timeFormat":"microseconds","metadata":{},"childs":[]},{"key":"Classify Image","elapsedTime":2140289,"timeFormat":"microseconds","metadata":{},"childs":[]},{"key":"Update Repo","elapsedTime":2299,"timeFormat":"microseconds","metadata":{},"childs":[]},{"key":"Loading of images","elapsedTime":127,"timeFormat":"microseconds","metadata":{},"childs":[]},{"key":"Classify Image","elapsedTime":2181983,"timeFormat":"microseconds","metadata":{},"childs":[]},{"key":"Update Repo","elapsedTime":1968,"timeFormat":"microseconds","metadata":{},"childs":[]},{"key":"Loading of images","elapsedTime":104,"timeFormat":"microseconds","metadata":{},"childs":[]},{"key":"Classify Image","elapsedTime":2117839,"timeFormat":"microseconds","metadata":{},"childs":[]},{"key":"Update Repo","elapsedTime":7183,"timeFormat":"microseconds","metadata":{},"childs":[]},{"key":"Loading of images","elapsedTime":102,"timeFormat":"microseconds","metadata":{},"childs":[]},{"key":"Classify Image","elapsedTime":2233483,"timeFormat":"microseconds","metadata":{},"childs":[]},{"key":"Update Repo","elapsedTime":2087,"timeFormat":"microseconds","metadata":{},"childs":[]},{"key":"Loading of images","elapsedTime":92,"timeFormat":"microseconds","metadata":{},"childs":[]},{"key":"Classify Image","elapsedTime":1887550,"timeFormat":"microseconds","metadata":{},"childs":[]},{"key":"Update Repo","elapsedTime":1980,"timeFormat":"microseconds","metadata":{},"childs":[]},{"key":"Loading of images","elapsedTime":106,"timeFormat":"microseconds","metadata":{},"childs":[]},{"key":"Classify Image","elapsedTime":2247694,"timeFormat":"microseconds","metadata":{},"childs":[]},{"key":"Update Repo","elapsedTime":658,"timeFormat":"microseconds","metadata":{},"childs":[]},{"key":"Loading of images","elapsedTime":129,"timeFormat":"microseconds","metadata":{},"childs":[]},{"key":"Classify Image","elapsedTime":2402330,"timeFormat":"microseconds","metadata":{},"childs":[]},{"key":"Update Repo","elapsedTime":1767,"timeFormat":"microseconds","metadata":{},"childs":[]},{"key":"Loading of images","elapsedTime":115,"timeFormat":"microseconds","metadata":{},"childs":[]},{"key":"Classify Image","elapsedTime":2030358,"timeFormat":"microseconds","metadata":{},"childs":[]},{"key":"Update Repo","elapsedTime":754,"timeFormat":"microseconds","metadata":{},"childs":[]},{"key":"Loading of images","elapsedTime":98,"timeFormat":"microseconds","metadata":{},"childs":[]},{"key":"Classify Image","elapsedTime":2131667,"timeFormat":"microseconds","metadata":{},"childs":[]},{"key":"Update Repo","elapsedTime":1773,"timeFormat":"microseconds","metadata":{},"childs":[]},{"key":"Loading of images","elapsedTime":100,"timeFormat":"microseconds","metadata":{},"childs":[]},{"key":"Classify Image","elapsedTime":2068794,"timeFormat":"microseconds","metadata":{},"childs":[]},{"key":"Update Repo","elapsedTime":2430,"timeFormat":"microseconds","metadata":{},"childs":[]},{"key":"Loading of images","elapsedTime":116,"timeFormat":"microseconds","metadata":{},"childs":[]},{"key":"Classify Image","elapsedTime":2037429,"timeFormat":"microseconds","metadata":{},"childs":[]},{"key":"Update Repo","elapsedTime":2485,"timeFormat":"microseconds","metadata":{},"childs":[]},{"key":"Loading of images","elapsedTime":103,"timeFormat":"microseconds","metadata":{},"childs":[]},{"key":"Classify Image","elapsedTime":2144110,"timeFormat":"microseconds","metadata":{},"childs":[]},{"key":"Update Repo","elapsedTime":9265,"timeFormat":"microseconds","metadata":{},"childs":[]},{"key":"Loading of images","elapsedTime":264,"timeFormat":"microseconds","metadata":{},"childs":[]},{"key":"Classify Image","elapsedTime":1804253,"timeFormat":"microseconds","metadata":{},"childs":[]},{"key":"Update Repo","elapsedTime":1518,"timeFormat":"microseconds","metadata":{},"childs":[]},{"key":"Loading of images","elapsedTime":149,"timeFormat":"microseconds","metadata":{},"childs":[]},{"key":"Classify Image","elapsedTime":1561619,"timeFormat":"microseconds","metadata":{},"childs":[]},{"key":"Update Repo","elapsedTime":925,"timeFormat":"microseconds","metadata":{},"childs":[]},{"key":"Loading of images","elapsedTime":119,"timeFormat":"microseconds","metadata":{},"childs":[]},{"key":"Classify Image","elapsedTime":1436389,"timeFormat":"microseconds","metadata":{},"childs":[]},{"key":"Update Repo","elapsedTime":2398,"timeFormat":"microseconds","metadata":{},"childs":[]}]}]}